multiplespawner/__init__.py
multiplespawner/helpers.py
multiplespawner/session.py
multiplespawner/util.py
multiplespawner/orchestration/__init__.py
multiplespawner/orchestration/orchestration.py
multiplespawner/runtime/__init__.py
multiplespawner/runtime/consts.py
multiplespawner/runtime/resource.py
multiplespawner/spawner/__init__.py
multiplespawner/spawner/configuration.py
multiplespawner/spawner/deployment.py
multiplespawner/spawner/multiple.py
multiplespawner/spawner/scheduler.py
multiplespawner/spawner/selection.py
multiplespawner/spawner/template.py
multiplespawner-0.0.0a5.dist-info/LICENSE
multiplespawner-0.0.0a5.dist-info/METADATA
multiplespawner-0.0.0a5.dist-info/WHEEL
multiplespawner-0.0.0a5.dist-info/top_level.txt
multiplespawner-0.0.0a5.dist-info/RECORD
