Metadata-Version: 2.1
Name: multiplespawner
Version: 0.0.0a5
Summary: UNKNOWN
Home-page: https://github.com/ucphhpc/multiplespawner
Author: Rasmus Munk
Author-email: munk1@live.dk
License: MIT
Keywords: JupyterHub,Spawner
Platform: UNKNOWN
Classifier: Intended Audience :: Developers
Classifier: Intended Audience :: System Administrators
Classifier: License :: OSI Approved :: MIT License
Classifier: Programming Language :: Python :: 3.6
Classifier: Programming Language :: Python :: 3.7
Classifier: Programming Language :: Python :: 3.8
Classifier: Programming Language :: Python :: 3.9
Requires-Dist: jupyterhub
Requires-Dist: traitlets
Requires-Dist: corc (==0.0.2a7)
Provides-Extra: dev
Requires-Dist: flake8 (==3.8.4) ; extra == 'dev'
Requires-Dist: black (==20.8b1) ; extra == 'dev'
Provides-Extra: test
Requires-Dist: flake8 (==3.8.4) ; extra == 'test'
